bibsanity/__init__.py
bibsanity/cache.py
bibsanity/cli.py
bibsanity/core.py
bibsanity/providers.py
bibsanity/report.py
bibsanity/utils.py
bibsanity-0.1.1.dist-info/licenses/LICENSE
bibsanity-0.1.1.dist-info/METADATA
bibsanity-0.1.1.dist-info/WHEEL
bibsanity-0.1.1.dist-info/entry_points.txt
bibsanity-0.1.1.dist-info/top_level.txt
bibsanity-0.1.1.dist-info/RECORD
